{
	"partitions" : [
		{
			"name" : "Top",
			"pins" : [
				{
					"name" : "display1[0]",
					"strict" : false
				},
				{
					"name" : "display1[1]",
					"strict" : false
				},
				{
					"name" : "display1[2]",
					"strict" : false
				},
				{
					"name" : "display1[3]",
					"strict" : false
				},
				{
					"name" : "display1[4]",
					"strict" : false
				},
				{
					"name" : "display1[5]",
					"strict" : false
				},
				{
					"name" : "display1[6]",
					"strict" : false
				},
				{
					"name" : "selectorLedDisplay[0]",
					"strict" : false
				},
				{
					"name" : "selectorLedDisplay[1]",
					"strict" : false
				},
				{
					"name" : "selectorLedDisplay[2]",
					"strict" : false
				},
				{
					"name" : "selectorLedDisplay[3]",
					"strict" : false
				},
				{
					"name" : "carry",
					"strict" : false
				},
				{
					"name" : "cero",
					"strict" : false
				},
				{
					"name" : "selector[0]",
					"strict" : false
				},
				{
					"name" : "selector[1]",
					"strict" : false
				},
				{
					"name" : "selector[2]",
					"strict" : false
				},
				{
					"name" : "selector[3]",
					"strict" : false
				},
				{
					"name" : "entrada2[0]",
					"strict" : false
				},
				{
					"name" : "entrada1[0]",
					"strict" : false
				},
				{
					"name" : "entrada1[1]",
					"strict" : false
				},
				{
					"name" : "entrada2[1]",
					"strict" : false
				},
				{
					"name" : "entrada1[2]",
					"strict" : false
				},
				{
					"name" : "entrada1[3]",
					"strict" : false
				},
				{
					"name" : "entrada2[2]",
					"strict" : false
				},
				{
					"name" : "entrada2[3]",
					"strict" : false
				}
			]
		}
	]
}